handshake
tests
