Metadata-Version: 2.1
Name: handshake
Version: 0.2.1
Summary: A Python library to create and validate authentication tokens.
Home-page: https://github.com/meeb/handshake
Author: https://github.com/meeb
Author-email: meeb@meeb.org
License: BSD
Keywords: handshake,auth,tokens,authentication,tickets
Platform: UNKNOWN
Classifier: Development Status :: 5 - Production/Stable
Classifier: Environment :: Web Environment
Classifier: Intended Audience :: Developers
Classifier: License :: OSI Approved :: BSD License
Classifier: Operating System :: OS Independent
Classifier: Programming Language :: Python
Classifier: Programming Language :: Python :: 3
Classifier: Topic :: Software Development :: Libraries :: Python Modules
